.coveragerc
.gitignore
.readthedocs.yml
AUTHORS.md
CHANGELOG.md
CONTRIBUTING.md
LICENSE.txt
README.md
pyproject.toml
requirements.txt
setup.cfg
setup.py
tox.ini
docs/Makefile
docs/authors.md
docs/changelog.md
docs/conf.py
docs/contributing.md
docs/index.md
docs/license.md
docs/readme.md
docs/requirements.txt
docs/_static/.gitignore
src/jiraclui/__init__.py
src/jiraclui/cli_app.py
src/jiraclui/helper.py
src/jiraclui/jira_board.py
src/jiraclui/jira_client.py
src/jiraclui/jira_handler.py
src/jiraclui/logger.py
src/jiraclui/main.py
src/jiraclui.egg-info/PKG-INFO
src/jiraclui.egg-info/SOURCES.txt
src/jiraclui.egg-info/dependency_links.txt
src/jiraclui.egg-info/entry_points.txt
src/jiraclui.egg-info/not-zip-safe
src/jiraclui.egg-info/requires.txt
src/jiraclui.egg-info/top_level.txt
tests/conftest.py
tests/test_skeleton.py