Metadata-Version: 2.1
Name: jiraclui
Version: 1.0.3
Summary: Add a short description here!
Home-page: https://github.com/gruppferi/jiraclui
Author: Ferdows Shahryar
Author-email: s.ferdows@hotmail.com
License: MIT
Platform: any
Classifier: Development Status :: 4 - Beta
Classifier: Programming Language :: Python
License-File: LICENSE.txt
Requires-Dist: importlib-metadata; python_version < "3.8"
Requires-Dist: importlib_metadata>=4.6.4
Requires-Dist: jira>=3.6.0
Requires-Dist: pytest>=8.0.0
Requires-Dist: PyYAML>=6.0.1
Requires-Dist: questionary>=2.0.1
Requires-Dist: rich>=13.7.0
Provides-Extra: testing
Requires-Dist: setuptools; extra == "testing"
Requires-Dist: pytest; extra == "testing"
Requires-Dist: pytest-cov; extra == "testing"
